json_line_logger/__init__.py
json_line_logger/version.py
json_line_logger-0.0.10.dist-info/licenses/LICENSE
json_line_logger-0.0.10.dist-info/METADATA
json_line_logger-0.0.10.dist-info/WHEEL
json_line_logger-0.0.10.dist-info/top_level.txt
json_line_logger-0.0.10.dist-info/RECORD
