Metadata-Version: 2.4
Name: json_line_logger
Version: 0.0.10
Summary: Configs for python's logging library to have a JSONL-log
Home-page: https://github.com/cherenkov-plenoscope/json_line_logger
Author: Sebastian Achim Mueller
Author-email: sebastian-achim.mueller@mpi-hd.mpg.de
Classifier: Programming Language :: Python :: 3
Classifier: License :: OSI Approved :: MIT License
Classifier: Operating System :: OS Independent
Classifier: Natural Language :: English
License-File: LICENSE
Requires-Dist: json_lines>=0.5.0
Dynamic: author
Dynamic: author-email
Dynamic: classifier
Dynamic: description
Dynamic: description-content-type
Dynamic: home-page
Dynamic: license-file
Dynamic: requires-dist
Dynamic: summary
